test_application/__init__.py
test_application/test_application.py
test_application-0.2.2.dist-info/LICENSE
test_application-0.2.2.dist-info/METADATA
test_application-0.2.2.dist-info/WHEEL
test_application-0.2.2.dist-info/entry_points.txt
test_application-0.2.2.dist-info/top_level.txt
test_application-0.2.2.dist-info/RECORD
