Metadata-Version: 2.1
Name: test-application
Version: 0.2.2
Summary: do random stuff
Home-page: https://github.com/JonasPammer/cookiecutter-pypackage-test
Author: Jonas Pammer
Author-email: opensource@jonaspammer.at
License: MIT
Classifier: Development Status :: 2 - Pre-Alpha
Classifier: Environment :: Console
Classifier: License :: OSI Approved :: MIT License
Classifier: Natural Language :: English
Classifier: Operating System :: POSIX :: Linux
Classifier: Programming Language :: Python :: 3
Classifier: Programming Language :: Python :: 3 :: Only
Classifier: Programming Language :: Python :: 3.7
Classifier: Programming Language :: Python :: 3.8
Classifier: Programming Language :: Python :: 3.9
Classifier: Programming Language :: Python :: 3.10
Classifier: Programming Language :: Python :: Implementation :: CPython
Classifier: Programming Language :: Python :: Implementation :: PyPy
Classifier: Typing :: Typed
Requires-Python: >=3.7
License-File: LICENSE
Requires-Dist: Click (>=8.0)
Requires-Dist: attrs (>=21.0)
Requires-Dist: pyyaml
Requires-Dist: types-PyYAML
